src/synapse/__init__.py
src/synapse/driver.py
synapse_lib-0.1.1.dist-info/WHEEL
synapse_lib-0.1.1.dist-info/METADATA
synapse_lib-0.1.1.dist-info/RECORD
