Metadata-Version: 2.1
Name: synapse-lib
Version: 0.1.1
Summary: Lorem Ipsum
Author: Dieter Buehler
Requires-Python: >=3.10,<4.0
Classifier: Programming Language :: Python :: 3
Classifier: Programming Language :: Python :: 3.10
